README.md
setup.cfg
setup.py
testdistributions/Binomialdistribution.py
testdistributions/Gaussiandistribution.py
testdistributions/Generaldistribution.py
testdistributions/__init__.py
testdistributions.egg-info/PKG-INFO
testdistributions.egg-info/SOURCES.txt
testdistributions.egg-info/dependency_links.txt
testdistributions.egg-info/not-zip-safe
testdistributions.egg-info/top_level.txt